{
  "1": {
    "name": "abdelrahmen",
    "score": 9600
  },
  "2": {
    "name": "addin",
    "score": 8480
  },
  "3": {
    "name": "addin",
    "score": 7920
  },
  "4": {
    "name": "Jr",
    "score": 7440
  },
  "5": {
    "name": "Jr",
    "score": 7360
  },
  "6": {
    "name": "Abdelrahmen",
    "score": 7040
  },
  "7": {
    "name": "Player",
    "score": 6560
  },
  "8": {
    "name": "addin",
    "score": 6480
  },
  "9": {
    "name": "Player",
    "score": 6240
  },
  "10": {
    "name": "Player",
    "score": 6160
  },
  "11": {
    "name": "Player",
    "score": 5840
  },
  "12": {
    "name": "abdelrahmen",
    "score": 5760
  },
  "13": {
    "name": "addin",
    "score": 5440
  },
  "14": {
    "name": "just Ahmed",
    "score": 5200
  },
  "15": {
    "name": "addin",
    "score": 5040
  },
  "16": {
    "name": "Player",
    "score": 4880
  },
  "17": {
    "name": "Player",
    "score": 4000
  },
  "18": {
    "name": "addin",
    "score": 3120
  },
  "19": {
    "name": "addin",
    "score": 3120
  },
  "20": {
    "name": "Player",
    "score": 2960
  },
  "21": {
    "name": "abderrahim",
    "score": 2800
  },
  "22": {
    "name": "Player",
    "score": 2640
  },
  "23": {
    "name": "addin",
    "score": 2480
  },
  "24": {
    "name": "Player",
    "score": 2080
  },
  "25": {
    "name": "Player",
    "score": 2000
  },
  "26": {
    "name": "Player",
    "score": 2000
  },
  "27": {
    "name": "Player",
    "score": 1760
  },
  "28": {
    "name": "Player",
    "score": 1600
  },
  "29": {
    "name": "abderrahim",
    "score": 1600
  },
  "30": {
    "name": "Player",
    "score": 1520
  },
  "31": {
    "name": "Player",
    "score": 1520
  },
  "32": {
    "name": "Player",
    "score": 1440
  },
  "33": {
    "name": "addin",
    "score": 1440
  },
  "34": {
    "name": "abderrahim",
    "score": 1280
  },
  "35": {
    "name": "Player",
    "score": 1200
  },
  "36": {
    "name": "Player",
    "score": 960
  },
  "37": {
    "name": "Player",
    "score": 960
  },
  "38": {
    "name": "Player",
    "score": 960
  },
  "39": {
    "name": "abderrahim",
    "score": 960
  },
  "40": {
    "name": "Jr",
    "score": 880
  },
  "41": {
    "name": "Player",
    "score": 720
  },
  "42": {
    "name": "Player",
    "score": 720
  },
  "43": {
    "name": "Player",
    "score": 720
  },
  "44": {
    "name": "Player",
    "score": 720
  },
  "45": {
    "name": "addin",
    "score": 720
  },
  "46": {
    "name": "Player",
    "score": 640
  },
  "47": {
    "name": "addin",
    "score": 640
  },
  "48": {
    "name": "abdelrahmen",
    "score": 480
  },
  "49": {
    "name": "Jr",
    "score": 480
  },
  "50": {
    "name": "Player",
    "score": 480
  },
  "51": {
    "name": "Player",
    "score": 400
  },
  "52": {
    "name": "Player",
    "score": 400
  },
  "53": {
    "name": "adel",
    "score": 320
  },
  "54": {
    "name": "adel",
    "score": 240
  },
  "55": {
    "name": "abderrahim",
    "score": 240
  },
  "56": {
    "name": "abderrahim",
    "score": 240
  },
  "57": {
    "name": "adel",
    "score": 160
  },
  "58": {
    "name": "Player",
    "score": 160
  },
  "59": {
    "name": "abdelrahmen",
    "score": 160
  },
  "60": {
    "name": "Player",
    "score": 160
  },
  "61": {
    "name": "adel",
    "score": 80
  },
  "62": {
    "name": "Player",
    "score": 80
  },
  "63": {
    "name": "Player",
    "score": 80
  },
  "64": {
    "name": "Player",
    "score": 80
  },
  "65": {
    "name": "Player",
    "score": 80
  },
  "66": {
    "name": "Player",
    "score": 80
  },
  "67": {
    "name": "Player",
    "score": 80
  },
  "68": {
    "name": "abdelrahmen",
    "score": 80
  },
  "69": {
    "name": "adel",
    "score": 0
  },
  "70": {
    "name": "Player",
    "score": 0
  }
}